ascvid/__init__.py
ascvid/__main__.py
ascvid/audio.py
ascvid/cli.py
ascvid/getcol.py
ascvid/logger.py
ascvid/player.py
ascvid/run_terminal.py
ascvid/timer.py
ascvid/subs/__init__.py
ascvid/subs/find_format.py
ascvid/subs/srt/__init__.py
ascvid/utils/html2curses.py
ascvid-1.5.3.dist-info/LICENSE
ascvid-1.5.3.dist-info/METADATA
ascvid-1.5.3.dist-info/WHEEL
ascvid-1.5.3.dist-info/entry_points.txt
ascvid-1.5.3.dist-info/top_level.txt
ascvid-1.5.3.dist-info/RECORD
