Metadata-Version: 2.1
Name: ascvid
Version: 1.5.3
Summary: ASCII Video player.
Home-page: https://github.com/jenca-adam/ascvid
Author: Adam Jenca
Author-email: jenca.a@gjh.sk
Keywords: Video,ASCII,Terminal
Classifier: Development Status :: 4 - Beta
Classifier: Environment :: Console
Classifier: Intended Audience :: End Users/Desktop
Classifier: License :: OSI Approved :: GNU General Public License v3 (GPLv3)
Classifier: Operating System :: Microsoft :: Windows
Classifier: Operating System :: POSIX :: Linux
Classifier: Operating System :: Unix
Classifier: Programming Language :: Python :: 3.10
Classifier: Topic :: Multimedia :: Video :: Display
License-File: LICENSE
Requires-Dist: pillow
Requires-Dist: moviepy
Requires-Dist: cursor
Requires-Dist: numpy
Requires-Dist: click
Requires-Dist: sounddevice
Requires-Dist: av
Requires-Dist: imageio
